{
  "created_at": "2026-04-27T20:02:14.323719",
  "format_specs": {},
  "stage_status": "checkpoint",
  "current_stage": 1,
  "last_updated_at": "2026-04-27T20:08:05.609596",
  "context_map_json": "{\"research_question\": \"能源轉型下的農漁村綠能衝突\", \"working_hypothesis\": \"在能源轉型的壓力下，農漁村綠能衝突多半不是單純的「支持或反對綠能」，而是源自土地治理失衡、程序正義不足與收益分配不均。如果能透過更細緻的用地分區、在地參與決策與合作型商業模式，綠能有機會轉化為農漁村適應氣候與多元生計的新工具，而非單向開發的對象。\", \"topics\": [{\"topic_id\": \"core_1\", \"name\": \"國家能源轉型與再生能源目標\", \"domain\": \"能源政策\", \"description\": \"國家層級設定的能源轉型時間表、再生能源占比目標與減碳承諾，是推動各類綠能設施進入農漁村的總體結構背景。\", \"relevance\": \"core\", \"evidence_ids\": [1, 2, 3], \"confidence\": \"high\"}, {\"topic_id\": \"core_2\", \"name\": \"農地與漁塭的空間與土地使用管制\", \"domain\": \"土地利用與空間規劃\", \"description\": \"農地、漁塭在法規上的使用分區、變更程序與管制強度，決定綠能設施能否進入、以何種形式進入，是衝突的核心制度場域。\", \"relevance\": \"core\", \"evidence_ids\": [4, 5, 6, 7], \"confidence\": \"high\"}, {\"topic_id\": \"core_3\", \"name\": \"風力與太陽光電設施的選址與環境影響\", \"domain\": \"環境影響評估\", \"description\": \"風電與光電設施選址所造成的景觀變遷、生態衝擊、土壤鹽化、水文改變等，直接影響農漁生產與地方環境，是在地反對的重要來源。\", \"relevance\": \"core\", \"evidence_ids\": [8, 9, 10, 11], \"confidence\": \"high\"}, {\"topic_id\": \"core_4\", \"name\": \"農漁村居民的生計結構與脆弱性\", \"domain\": \"農村與漁村社會經濟\", \"description\": \"農民、漁民的收入來源、土地所有權與租賃關係、世代傳承與人口外流狀況，會影響他們對綠能開發風險與機會的感受。\", \"relevance\": \"core\", \"evidence_ids\": [12, 13, 14], \"confidence\": \"medium\"}, {\"topic_id\": \"core_5\", \"name\": \"程序正義與地方參與機制\", \"domain\": \"治理與公共參與\", \"description\": \"環評、公聽會、協商平台等程序是否讓在地社群實質參與、掌握資訊並有影響力，常被指為衝突是否升高的關鍵。\", \"relevance\": \"core\", \"evidence_ids\": [15, 16, 17], \"confidence\": \"high\"}, {\"topic_id\": \"core_6\", \"name\": \"綠能收益分配與在地回饋機制\", \"domain\": \"經濟與分配正義\", \"description\": \"地租、分潤、回饋金、社區基金等設計，決定綠能開發利潤如何在開發商、地主與一般居民之間分配，是支持與反對陣營的重要分水嶺。\", \"relevance\": \"core\", \"evidence_ids\": [18], \"confidence\": \"high\"}, {\"topic_id\": \"core_7\", \"name\": \"環境保護團體與農漁團體的立場差異\", \"domain\": \"社會運動與利益團體\", \"description\": \"環團重視生態保護與土地永續，農漁團體則著重生計、安全與產業發展，兩者在綠能管制鬆緊上的訴求常有分歧甚至衝突。\", \"relevance\": \"core\", \"evidence_ids\": [19, 20, 21], \"confidence\": \"high\"}, {\"topic_id\": \"core_8\", \"name\": \"法規修正與「矯枉過正」爭議\", \"domain\": \"法律與政策過程\", \"description\": \"光電環評與用地規範修法時，出現「擴大禁建」或「放寬用地」是否過頭的爭論，反映不同群體對風險與機會的評估落差。\", \"relevance\": \"core\", \"evidence_ids\": [], \"confidence\": \"high\"}, {\"topic_id\": \"core_9\", \"name\": \"能源轉型下的城市－鄉村權力與資源不對稱\", \"domain\": \"政治經濟學\", \"description\": \"都市用電需求與減碳壓力往往轉化為在農漁村布設設施，暴露出決策權掌握在城市菁英、成本卻由地方承擔的不平衡。\", \"relevance\": \"core\", \"evidence_ids\": [], \"confidence\": \"medium\"}, {\"topic_id\": \"sup_1\", \"name\": \"社區型電力與合作社模式\", \"domain\": \"治理模式與商業模式創新\", \"description\": \"由社區、合作社或地方政府主導的綠能開發與持有模式，可能減少外來資本主導帶來的不信任，是降低衝突的潛在解方。\", \"relevance\": \"supporting\", \"evidence_ids\": [], \"confidence\": \"medium\"}, {\"topic_id\": \"sup_2\", \"name\": \"重大氣候災害與農漁村能源韌性\", \"domain\": \"氣候適應與災害管理\", \"description\": \"風災、水災、停電等事件凸顯農漁村對穩定能源與備援系統的需求，使綠能同時被視為風險與機會。\", \"relevance\": \"supporting\", \"evidence_ids\": [], \"confidence\": \"medium\"}, {\"topic_id\": \"sup_3\", \"name\": \"地方政府在綠能治理中的角色\", \"domain\": \"地方治理\", \"description\": \"地方政府在審查、招商、溝通與調解中的權限與實務運作，會影響衝突的激化或緩解。\", \"relevance\": \"supporting\", \"evidence_ids\": [], \"confidence\": \"medium\"}, {\"topic_id\": \"sup_4\", \"name\": \"國際農電與漁電模式的經驗（如智利、德國）\", \"domain\": \"國際比較與政策學習\", \"description\": \"其他國家在農地上設置光電、風電的政策設計與衝突經驗，可作為理解本地問題與發展替代方案的鏡鑑。\", \"relevance\": \"supporting\", \"evidence_ids\": [], \"confidence\": \"high\"}, {\"topic_id\": \"sup_5\", \"name\": \"農漁村綠能衝突的社會認知與媒體再現\", \"domain\": \"媒體與公共論述\", \"description\": \"主流媒體與社群媒體如何呈現「綠能毀綠地」、「以農為本」等框架，會影響大眾對衝突的理解與政策壓力。\", \"relevance\": \"supporting\", \"evidence_ids\": [], \"confidence\": \"medium\"}, {\"topic_id\": \"sup_6\", \"name\": \"再生能源技術特性與空間需求\", \"domain\": \"能源技術與工程\", \"description\": \"風電、地面型光電、屋頂型光電、漁電共生等技術的容量因數、占地、並網條件與靈活度，決定它們對土地與環境的壓力。\", \"relevance\": \"supporting\", \"evidence_ids\": [], \"confidence\": \"high\"}, {\"topic_id\": \"sup_7\", \"name\": \"全資源整合型電力規劃與IRP工具\", \"domain\": \"能源規劃與模型\", \"description\": \"透過整合各種能源資源與需求管理的規劃工具（如IRP），尋求在碳減量、成本與社會衝突之間的折衷。\", \"relevance\": \"supporting\", \"evidence_ids\": [], \"confidence\": \"medium\"}, {\"topic_id\": \"sup_8\", \"name\": \"地方認同、景觀與文化資源\", \"domain\": \"文化與地方認同\", \"description\": \"農漁村的景觀、祭典、歷史記憶等文化面向，容易被大型綠能設施改變，造成居民的心理與情感衝擊。\", \"relevance\": \"supporting\", \"evidence_ids\": [], \"confidence\": \"medium\"}, {\"topic_id\": \"sup_9\", \"name\": \"能源轉型國際承諾與貿易壓力（如CBAM）\", \"domain\": \"國際關係與氣候治理\", \"description\": \"國際減碳規範、碳邊境調整機制等壓力，如何向內部轉化為加速綠能開發的正當性，進而施加在農漁村土地上。\", \"relevance\": \"supporting\", \"evidence_ids\": [], \"confidence\": \"medium\"}, {\"topic_id\": \"peri_1\", \"name\": \"能源轉型與健康、生活環境關聯\", \"domain\": \"公共健康與環境心理\", \"description\": \"能源設施對噪音、空氣品質、生活壓力等的影響，以及不同居住地與環境條件對健康的長期效應。\", \"relevance\": \"peripheral\", \"evidence_ids\": [], \"confidence\": \"low\"}, {\"topic_id\": \"peri_2\", \"name\": \"長期時間尺度下土地利用變遷\", \"domain\": \"歷史與土地變遷\", \"description\": \"農漁村土地從傳統農漁業、工業區、度假開發到綠能設施的長期變遷脈絡，有助於理解當前衝突是不是延續既有開發矛盾。\", \"relevance\": \"peripheral\", \"evidence_ids\": [], \"confidence\": \"medium\"}, {\"topic_id\": \"core_10\", \"name\": \"環評門檻爭議與制度設計\", \"domain\": \"環境影響評估與法制\", \"description\": \"圍繞太陽光電與風電的環境影響評估門檻，環保團體主張加嚴與產業團體主張放寬之間的拉扯，直接影響綠能在農漁村開發的速度與衝突強度。\", \"relevance\": \"core\", \"evidence_ids\": [13, 19, 20, 21], \"confidence\": \"high\"}], \"relations\": [{\"relation_id\": \"rel_1\", \"source_topic_id\": \"core_1\", \"target_topic_id\": \"core_2\", \"relation_type\": \"causes\", \"description\": \"國家提高再生能源目標與時程，促使農地與漁塭被視為潛在用地，帶動土地使用管制放寬或重議。\", \"evidence_ids\": [1, 4], \"confidence\": \"high\"}, {\"relation_id\": \"rel_2\", \"source_topic_id\": \"core_1\", \"target_topic_id\": \"core_3\", \"relation_type\": \"causes\", \"description\": \"能源轉型的量化目標增加對風電與光電設施的需求，導致選址壓力提高並擴散到農漁村。\", \"evidence_ids\": [2, 8], \"confidence\": \"high\"}, {\"relation_id\": \"rel_3\", \"source_topic_id\": \"core_2\", \"target_topic_id\": \"core_3\", \"relation_type\": \"enables\", \"description\": \"農地與漁塭用地管制的鬆綁，使在這些區域興建風光電設施在法律上成為可能，進而引發環境與生產影響。\", \"evidence_ids\": [4, 5, 9], \"confidence\": \"high\"}, {\"relation_id\": \"rel_4\", \"source_topic_id\": \"core_3\", \"target_topic_id\": \"core_4\", \"relation_type\": \"causes\", \"description\": \"風光電設施對水文、生態與耕作條件的改變，可能減損農漁生產，直接衝擊在地居民生計。\", \"evidence_ids\": [8, 10, 12], \"confidence\": \"high\"}, {\"relation_id\": \"rel_5\", \"source_topic_id\": \"core_4\", \"target_topic_id\": \"core_5\", \"relation_type\": \"supports\", \"description\": \"農漁村原本就較為脆弱的生計結構，使居民更加在意參與決策與保障權益，強化對程序正義的訴求。\", \"evidence_ids\": [12, 13, 15], \"confidence\": \"medium\"}, {\"relation_id\": \"rel_6\", \"source_topic_id\": \"core_5\", \"target_topic_id\": \"core_6\", \"relation_type\": \"enables\", \"description\": \"若有實質參與與協商機制，較容易談出被在地接受的收益分配與回饋設計。\", \"evidence_ids\": [15, 16, 18], \"confidence\": \"high\"}, {\"relation_id\": \"rel_7\", \"source_topic_id\": \"core_6\", \"target_topic_id\": \"core_3\", \"relation_type\": \"prevents\", \"description\": \"合理且在地可感的收益分配與回饋，可能降低因環境影響而引發的反對強度。\", \"evidence_ids\": [18], \"confidence\": \"medium\"}, {\"relation_id\": \"rel_8\", \"source_topic_id\": \"sup_1\", \"target_topic_id\": \"core_6\", \"relation_type\": \"enables\", \"description\": \"社區主導或合作社模式，通常能讓收益更多留在地方，改善分配不均的問題。\", \"evidence_ids\": [], \"confidence\": \"medium\"}, {\"relation_id\": \"rel_9\", \"source_topic_id\": \"sup_2\", \"target_topic_id\": \"sup_1\", \"relation_type\": \"supports\", \"description\": \"災害與停電經驗讓在地社群更重視能源自立，可能提升對社區型電力與合作模式的接受度。\", \"evidence_ids\": [], \"confidence\": \"medium\"}, {\"relation_id\": \"rel_10\", \"source_topic_id\": \"core_7\", \"target_topic_id\": \"core_8\", \"relation_type\": \"supports\", \"description\": \"環團與農漁團體對光電環評與用地規範的不同訴求，共同形塑了「擴大禁建是否矯枉過正」的公共爭論。\", \"evidence_ids\": [19, 20], \"confidence\": \"high\"}, {\"relation_id\": \"rel_11\", \"source_topic_id\": \"core_8\", \"target_topic_id\": \"core_2\", \"relation_type\": \"prevents\", \"description\": \"若修法走向加嚴與擴大禁建，會限制農地與漁塭作為綠能用地的可能性。\", \"evidence_ids\": [], \"confidence\": \"high\"}, {\"relation_id\": \"rel_12\", \"source_topic_id\": \"core_5\", \"target_topic_id\": \"core_8\", \"relation_type\": \"supports\", \"description\": \"程序正義與地方參與不足，容易導致地方社群要求透過更嚴格法規來補強保障。\", \"evidence_ids\": [15, 16], \"confidence\": \"medium\"}, {\"relation_id\": \"rel_13\", \"source_topic_id\": \"sup_4\", \"target_topic_id\": \"sup_1\", \"relation_type\": \"analogous_to\", \"description\": \"德國、智利等地的農電與社區電力實驗，可作為設計在地合作社模式的類比案例。\", \"evidence_ids\": [], \"confidence\": \"medium\"}, {\"relation_id\": \"rel_14\", \"source_topic_id\": \"sup_4\", \"target_topic_id\": \"core_2\", \"relation_type\": \"supports\", \"description\": \"國際經驗顯示，精細的用地分區與生態敏感區保護，是降低綠能衝突的重要前提。\", \"evidence_ids\": [5], \"confidence\": \"high\"}, {\"relation_id\": \"rel_15\", \"source_topic_id\": \"sup_5\", \"target_topic_id\": \"core_7\", \"relation_type\": \"supports\", \"description\": \"媒體對環團與農漁團體立場的選擇性呈現，會強化兩者之間的對立印象與互不信任。\", \"evidence_ids\": [19], \"confidence\": \"medium\"}, {\"relation_id\": \"rel_16\", \"source_topic_id\": \"sup_6\", \"target_topic_id\": \"core_3\", \"relation_type\": \"causes\", \"description\": \"不同再生能源技術對空間與環境的需求差異，導致實際的生態與景觀影響程度不同。\", \"evidence_ids\": [], \"confidence\": \"high\"}, {\"relation_id\": \"rel_17\", \"source_topic_id\": \"sup_6\", \"target_topic_id\": \"core_2\", \"relation_type\": \"supports\", \"description\": \"技術特性會反過來影響土地管制如何設計，例如鼓勵屋頂型而非地面型光電。\", \"evidence_ids\": [20], \"confidence\": \"high\"}, {\"relation_id\": \"rel_18\", \"source_topic_id\": \"sup_7\", \"target_topic_id\": \"core_1\", \"relation_type\": \"supports\", \"description\": \"全資源整合型電力規劃工具，提供國家設定與調整能源轉型目標與路徑的技術基礎。\", \"evidence_ids\": [1], \"confidence\": \"medium\"}, {\"relation_id\": \"rel_19\", \"source_topic_id\": \"core_9\", \"target_topic_id\": \"core_4\", \"relation_type\": \"causes\", \"description\": \"城市－鄉村在決策權與談判力上的不對稱，使農漁村在面對開發時更容易承受生計風險。\", \"evidence_ids\": [], \"confidence\": \"medium\"}, {\"relation_id\": \"rel_20\", \"source_topic_id\": \"core_9\", \"target_topic_id\": \"core_5\", \"relation_type\": \"supports\", \"description\": \"權力不對稱讓地方更加要求程序上的保障與透明，避免被「頭過身就過」。\", \"evidence_ids\": [15], \"confidence\": \"medium\"}, {\"relation_id\": \"rel_21\", \"source_topic_id\": \"sup_8\", \"target_topic_id\": \"core_3\", \"relation_type\": \"causes\", \"description\": \"綠能設施對景觀與文化場域的改變，會被在地感受為一種文化與身分的威脅，加劇衝突情緒。\", \"evidence_ids\": [8], \"confidence\": \"medium\"}, {\"relation_id\": \"rel_22\", \"source_topic_id\": \"peri_2\", \"target_topic_id\": \"core_2\", \"relation_type\": \"supports\", \"description\": \"長期土地利用變遷的歷史，說明目前的管制鬆綁或收緊其實是延續既有開發模式的爭議。\", \"evidence_ids\": [4], \"confidence\": \"medium\"}, {\"relation_id\": \"rel_23\", \"source_topic_id\": \"sup_9\", \"target_topic_id\": \"core_1\", \"relation_type\": \"supports\", \"description\": \"國際減碳與貿易壓力支撐了國家積極推動能源轉型的正當性與急迫性。\", \"evidence_ids\": [1], \"confidence\": \"medium\"}, {\"relation_id\": \"rel_24\", \"source_topic_id\": \"sup_9\", \"target_topic_id\": \"core_9\", \"relation_type\": \"causes\", \"description\": \"外部壓力被內部治理結構吸收後，往往透過在農漁村布設設施來滿足國家承諾，加劇城市－鄉村之間的資源不均。\", \"evidence_ids\": [], \"confidence\": \"medium\"}, {\"relation_id\": \"rel_25\", \"source_topic_id\": \"core_10\", \"target_topic_id\": \"core_3\", \"relation_type\": \"prevents\", \"description\": \"若太陽光電與風電的環評門檻加嚴，部分敏感或爭議較大的農漁村開發案可能被擋下或延後。\", \"evidence_ids\": [13, 19, 21], \"confidence\": \"high\"}, {\"relation_id\": \"rel_26\", \"source_topic_id\": \"core_10\", \"target_topic_id\": \"core_6\", \"relation_type\": \"supports\", \"description\": \"對環評門檻的爭論經常連帶牽涉到地方回饋與分潤是否足以補償環境風險。\", \"evidence_ids\": [13, 19, 21], \"confidence\": \"medium\"}, {\"relation_id\": \"rel_27\", \"source_topic_id\": \"core_7\", \"target_topic_id\": \"core_10\", \"relation_type\": \"supports\", \"description\": \"環團提出加嚴環評門檻的訴求、產業團體主張避免過度管制，共同構成環評制度設計的政治角力。\", \"evidence_ids\": [13, 19, 21], \"confidence\": \"high\"}, {\"relation_id\": \"rel_28\", \"source_topic_id\": \"sup_6\", \"target_topic_id\": \"core_10\", \"relation_type\": \"supports\", \"description\": \"屋頂優先與地面型光電環評門檻的討論，反映技術特性與制度設計的互動。\", \"evidence_ids\": [20], \"confidence\": \"high\"}], \"followup_questions\": [\"環團所提出的光電與風電環評加嚴訴求，在具體農漁村個案中如何影響開發進度與地方衝突？\", \"光電公協會等產業團體對環評修法的風險敘事（供電穩定、半導體競爭力、RE100）在地方農漁村的接受度如何？\", \"現行屋頂優先政策在農村與漁村的實際落實情況為何？是否真的減少地面型光電對農地與漁塭的壓力？\", \"是否有農漁村社區主動利用較嚴格的環評門檻作為談判工具，爭取更好的土地治理與收益分配？\"], \"search_seeds\": [{\"seed_id\": \"s1\", \"query\": \"台灣 農漁村 綠能 衝突 光電 風電 個案研究\", \"target_topic_id\": \"core_3\", \"rationale\": \"蒐集具體個案有助於具體化衝突成因與影響類型。\", \"source_strategy\": \"both\", \"priority\": \"high\", \"status\": \"pending\"}, {\"seed_id\": \"s2\", \"query\": \"台灣 農地 變更 綠能用地 法規 以農為本 原則\", \"target_topic_id\": \"core_2\", \"rationale\": \"釐清農地、漁塭作為綠能用地的現行法制基礎與爭議。\", \"source_strategy\": \"both\", \"priority\": \"high\", \"status\": \"pending\"}, {\"seed_id\": \"s3\", \"query\": \"光電 環評 修法 擴大禁建 矯枉過正 環團 農漁團體 立場\", \"target_topic_id\": \"core_8\", \"rationale\": \"理解修法過程中不同利害關係人對風險與機會的評估。\", \"source_strategy\": \"both\", \"priority\": \"high\", \"status\": \"executed\"}, {\"seed_id\": \"s4\", \"query\": \"台灣 農村 漁村 綠能 社區電力 合作社 模式 案例\", \"target_topic_id\": \"sup_1\", \"rationale\": \"尋找在地主導綠能的實務案例，作為潛在解方的依據。\", \"source_strategy\": \"both\", \"priority\": \"medium\", \"status\": \"pending\"}, {\"seed_id\": \"s5\", \"query\": \"Germany Energiewende community energy agrivoltaics fishing solar conflict\", \"target_topic_id\": \"sup_4\", \"rationale\": \"從德國等國家汲取農電與社區能源治理經驗。\", \"source_strategy\": \"both\", \"priority\": \"medium\", \"status\": \"pending\"}, {\"seed_id\": \"s6\", \"query\": \"智利 光電 計畫 爭議 農村 漁村 能源 發展 困境\", \"target_topic_id\": \"sup_4\", \"rationale\": \"延伸初始資料中的智利案例，理解其與台灣的可比性與差異。\", \"source_strategy\": \"both\", \"priority\": \"low\", \"status\": \"pending\"}, {\"seed_id\": \"s7\", \"query\": \"台灣 農漁村 綠能 收益分配 回饋金 地租 衝突\", \"target_topic_id\": \"core_6\", \"rationale\": \"掌握在地對收益分配不滿與創新分潤機制的具體爭議。\", \"source_strategy\": \"both\", \"priority\": \"high\", \"status\": \"pending\"}, {\"seed_id\": \"s8\", \"query\": \"全資源IRP 電力規劃 台灣 農漁村 衝突 評估\", \"target_topic_id\": \"sup_7\", \"rationale\": \"了解IRP等工具是否納入社會衝突或土地使用限制。\", \"source_strategy\": \"both\", \"priority\": \"medium\", \"status\": \"pending\"}, {\"seed_id\": \"s9\", \"query\": \"農漁村 綠能 衝突 媒體 報導 框架 分析\", \"target_topic_id\": \"sup_5\", \"rationale\": \"分析媒體如何建構「綠能毀綠地」與「以農為本」等論述。\", \"source_strategy\": \"both\", \"priority\": \"low\", \"status\": \"pending\"}, {\"seed_id\": \"s10\", \"query\": \"台灣 城鄉 能源轉型 權力不對稱 土地正義\", \"target_topic_id\": \"core_9\", \"rationale\": \"從政治經濟視角整理城市－鄉村在能源轉型中的結構不平等。\", \"source_strategy\": \"both\", \"priority\": \"medium\", \"status\": \"pending\"}, {\"seed_id\": \"s11\", \"query\": \"綠能發展 要順利 環評門檻 應加嚴 聯合聲明 農漁村\", \"target_topic_id\": \"core_10\", \"rationale\": \"理解環團等利害關係人要求加嚴環評門檻的理由及其對農漁村綠能衝突的影響。\", \"source_strategy\": \"web\", \"priority\": \"high\", \"status\": \"executed\"}, {\"seed_id\": \"s12\", \"query\": \"屋頂優先 環境永續 穩健推動 太陽光電發展 農地\", \"target_topic_id\": \"sup_6\", \"rationale\": \"理解政府推動屋頂優先政策與環境永續論述如何回應農地光電爭議。\", \"source_strategy\": \"web\", \"priority\": \"high\", \"status\": \"executed\"}, {\"seed_id\": \"s13\", \"query\": \"環評法修法 對綠電衝擊多大 光電公協會 供電穩定 半導體 RE100\", \"target_topic_id\": \"core_10\", \"rationale\": \"掌握產業團體對環評修法的憂慮與論述，平衡環團立場。\", \"source_strategy\": \"web\", \"priority\": \"high\", \"status\": \"executed\"}], \"version\": 12, \"revision_history\": [{\"from_version\": 11, \"to_version\": 12, \"added_topics\": [\"core_10\"], \"removed_topics\": [], \"modified_topics\": [\"core_8\", \"sup_6\"], \"added_relations\": [\"rel_25\", \"rel_26\", \"rel_27\", \"rel_28\"], \"removed_relations\": [], \"reason\": \"新資料聚焦於環評門檻與屋頂優先政策，顯示環評制度設計本身是獨立且關鍵的爭議場域，需從原本的修法爭議中抽離成為新的核心面向，並補上技術與制度互動的關聯。\", \"timestamp\": \"2026-05-27T00:00:00Z\"}], \"created_at\": \"2026-05-20T00:00:00Z\", \"last_refined_at\": \"2026-05-27T00:00:00Z\"}",
  "written_sections": [],
  "checkpoint_prompt": "## 研究結構提案\n\n**研究問題**：台灣能源政策\n**工作假設**：台灣能源政策的關鍵在於如何在穩定供電、產業競爭力與淨零轉型之間取得平衡，而目前在非核家園路線、再生能源推動速度、電價結構與社會溝通上存在結構性矛盾與執行落差，導致缺電焦慮與政治極化。\n\n1. **台灣電力供需現況與缺電爭議**（核心）— 分析台灣目前電力供給、需求成長（特別是半導體與AI產業用電）、備轉容量與過去數次限電事件，釐清「缺電」是結構問題還是治理與溝通問題。\n2. **非核家園政策與核能爭議**（核心）— 檢視台灣非核家園政策的背景、目標與實際進程，以及不同政治與產業利害關係人對核能延役、重啟的支持與反對論述，並關注近期《核管法》修法對延役與重啟的制度變化。\n3. **再生能源發展目標與進度（風電、太陽能）**（核心）— 整理台灣離岸風電與太陽光電的裝置容量目標、實際進度、政策工具與面臨的瓶頸，例如地面型光電阻礙、許可流程與電網接入等，並納入2025年發電占比從20%調降為約15.2%的政策調整。\n4. **臺灣淨零排放與能源轉型策略**（核心）— 說明台灣2050淨零目標與中程減碳路徑，包含能源結構調整、產業減碳與碳定價政策，及與國際淨零趨勢的連結，並結合行政院與國發會的官方淨零路徑與關鍵戰略行動計畫。\n5. **半導體與AI產業用電需求與競爭力**（核心）— 探討半導體與AI伺服器等高耗能產業對電力品質與穩定度的要求，以及電價、供電風險與區域供電限制（如中電北送瓶頸、AI資料中心併網限制）如何影響投資決策與產業去留。\n6. **能源政策的政黨競爭與意識形態**（核心）— 分析不同政黨在核能、再生能源、煤氣比例等議題上的立場差異，以及意識形態如何形塑政策選項與社會分歧，並關注公投實務與近期《核管法》修法等政治事件。\n7. **再生能源設置的土地與社會衝突**（核心）— 聚焦地面型太陽能、風機設置與漁業、農業、景觀、生態及地方居民之間的衝突與協商機制，包括沿海及不利耕作農地優先布建政策與地方推動力道隨選舉變化。\n8. **關鍵利害關係人與利益分配**（核心）— 盤點中央政府、地方政府、國營事業（如台電）、半導體與製造業者、再生能源開發商、環保團體與地方居民等角色及其利益衝突，並關注科技業被動員支持電廠與地方自治互動。\n9. **社會溝通、風險認知與信任**（核心）— 探討政府在能源政策上資訊公開、風險溝通與參與機制，及媒體與社群如何影響大眾對缺電、核能與再生能源的認知，包括對再生能源事故與錯假訊息的擴散。\n10. **電力即國力：能源與國家安全**（輔助）— 從「電力即國力」的觀點，分析能源供應安全與備援能力如何影響台灣在地緣政治、經貿談判與產業布局上的韌性。\n11. **電價結構與政治經濟**（輔助）— 檢視台灣民生與產業電價、補貼與凍漲政策，如何反映或扭曲能源成本，並對節能誘因與財政負擔造成影響。\n12. **環保與空污、健康風險**（輔助）— 整理燃煤、天然氣以及再生能源設置對空氣品質、生態與居民健康的影響，並評估不同能源組合的環境代價。\n13. **能源轉型的產業機會與綠色成長**（輔助）— 探討再生能源、儲能、智慧電網與節能技術在台灣可能創造的產業與就業機會，以及「經濟日不落國」等口號與實際政策落差，並結合近期儲能與電網產業投資與商機。\n14. **國際能源轉型經驗比較（德國、日本、韓國）**（輔助）— 比較德國能源轉型、日本核災後能源路線、韓國減核/再核等案例，找出台灣在制度設計與社會溝通上的可借鏡之處。\n15. **電網基礎建設與儲能系統**（輔助）— 分析台灣電網老化、區域供電不均與再生能源併網挑戰，以及儲能技術、智慧電網與相關觀音瓶頸在提升穩定供電與電網韌性中的角色。\n16. **長期能源情境規劃與路徑模擬**（輔助）— 檢視官方與學界對不同能源配比（核、氣、煤、再生）的情境模擬與成本效益分析，作為政策選擇的量化基礎。\n17. **國際貿易、碳邊境調整與供應鏈壓力**（輔助）— 說明歐盟CBAM等國際碳規範對台灣出口產業的壓力，如何反向推動國內能源結構調整與減碳。\n18. **能源技術創新與在地研發能力**（周邊）— 評估台灣在儲能、氫能、再生能源設備製造與智慧能源管理等技術上的研發與產業化能力，並結合國際淨零科技趨勢與國內淨零技術布局。\n19. **災害、極端氣候與能源系統韌性**（周邊）— 分析颱風、地震與極端高溫等對發電與輸配電系統的衝擊，以及韌性規劃（如微電網與分散式能源）在能源政策中的重要性，並結合再生能源設施在極端氣候下受損與傳播爭議案例。\n20. **地方能源自治與社區型能源模式**（周邊）— 探討地方政府或社區參與的能源合作社、公民電廠、社區電廠等模式，是否能緩和地方反彈並提升再生能源接受度。\n\n**待探索的問題**：\n- 台灣過去十年實際發生的限電與大規模跳電事件，其主因是設備老化、操作失誤、極端氣候，還是結構性供電不足？\n- 非核家園政策若做技術性調整（如延役），在法律、政治與社會接受度上最大的障礙是什麼？\n- 目前再生能源裝置容量與發電占比的實際數據為何，與原先目標相比落差多大？\n- 半導體與AI產業未來十到二十年的用電需求預測為何，現有供電規劃是否足以因應？\n- 國際上有哪些成功降低地方再生能源衝突的治理模式，台灣是否已有試點案例？\n- 台灣電價若反映真實成本與碳排放，對不同所得族群與產業的影響為何，有哪些配套可減緩衝擊？\n- 德國、日本與韓國在能源轉型過程中，如何在核能去留、再生能源擴張與電價承受之間做取捨？\n- 台灣在國際碳邊境調整與供應鏈減碳壓力下，能源結構調整的時間壓力有多大？\n- 台電大學微電網與聚落式微電網示範計畫的技術與治理成果為何，對提升電網韌性與分散式能源有何啟示？\n- 台灣目前在氫能、去碳燃氫與碳捕捉等前瞻能源技術上的研發與示範規模為何，是否已納入國家能源政策主軸？\n\n這是我整理的研究結構，你覺得如何？需要調整嗎？",
  "executed_searches": [
    "台灣 能源技術 創新 在地 研發 儲能 氫能 智慧電網 學術論文 政策 報告",
    "台灣 能源系統 韌性 颱風 地震 極端高溫 供電 中斷 研究 報告",
    "台灣 社區 電廠 能源 合作社 地方能源自治 案例 研究",
    "Germany Japan Korea energy transition nuclear phase-out community energy projects comparison",
    "台灣 能源 韌性 分散式電源 微電網 政策 規劃",
    "\"台灣電價結構\" 補貼 凍漲 對再生能源投資 研究 報告",
    "台灣 2050 淨零 排放 路徑 能源 結構 調整 2050路徑藍圖 PDF",
    "台灣 半導體 用電 需求 預測 AI 數據中心 2030 2040 台電 規劃",
    "台灣 再生能源 裝置容量 發電占比 目標 達成率 2020..2025 統計",
    "台灣 再生能源 地面型 太陽光電 土地 使用 衝突 屏東 彰化 雲林 個案 研究",
    "非核家園 政策 立法 施行條例 延役 法律爭議 解釋 公投 結果 分析",
    "台灣 能源 政策 民意 調查 核能 再生能源 缺電 風險認知 2020..2024",
    "Germany Japan Korea energy transition electricity price impact comparison 2015..2024",
    "台灣 電網 老化 再生能源 併網 儲能 建設計畫 2020..2025 進度 評估"
  ],
  "completed_sections": [],
  "style_features_json": "",
  "initial_context_map_json": "{\"research_question\":\"台灣能源政策\",\"working_hypothesis\":\"台灣能源政策的關鍵在於如何在穩定供電、產業競爭力與淨零轉型之間取得平衡，而目前在非核家園路線、再生能源推動速度、電價結構與社會溝通上存在結構性矛盾與執行落差，導致缺電焦慮與政治極化。\",\"topics\":[{\"topic_id\":\"t1\",\"name\":\"台灣電力供需現況與缺電爭議\",\"domain\":\"能源政策\",\"description\":\"分析台灣目前電力供給、需求成長（特別是半導體與AI產業用電）、備轉容量與過去數次限電事件，釐清「缺電」是結構問題還是治理與溝通問題。\",\"relevance\":\"core\",\"evidence_ids\":[1,2,6,7,8,9],\"confidence\":\"high\"},{\"topic_id\":\"t2\",\"name\":\"非核家園政策與核能爭議\",\"domain\":\"能源政策\",\"description\":\"檢視台灣非核家園政策的背景、目標與實際進程，以及不同政治與產業利害關係人對核能延役、重啟的支持與反對論述。\",\"relevance\":\"core\",\"evidence_ids\":[1,10],\"confidence\":\"high\"},{\"topic_id\":\"t3\",\"name\":\"再生能源發展目標與進度（風電、太陽能）\",\"domain\":\"再生能源\",\"description\":\"整理台灣離岸風電與太陽光電的裝置容量目標、實際進度、政策工具與面臨的瓶頸，例如地面型光電阻礙、許可流程與電網接入等。\",\"relevance\":\"core\",\"evidence_ids\":[4,5,6],\"confidence\":\"high\"},{\"topic_id\":\"t4\",\"name\":\"臺灣淨零排放與能源轉型策略\",\"domain\":\"氣候政策\",\"description\":\"說明台灣2050淨零目標與中程減碳路徑，包含能源結構調整、產業減碳與碳定價政策，及與國際淨零趨勢的連結。\",\"relevance\":\"core\",\"evidence_ids\":[4],\"confidence\":\"medium\"},{\"topic_id\":\"t5\",\"name\":\"半導體與AI產業用電需求與競爭力\",\"domain\":\"產業政策\",\"description\":\"探討半導體與AI伺服器等高耗能產業對電力品質與穩定度的要求，以及電價、供電風險如何影響投資決策與產業去留。\",\"relevance\":\"core\",\"evidence_ids\":[1,2,6,7,9],\"confidence\":\"high\"},{\"topic_id\":\"t6\",\"name\":\"電力即國力：能源與國家安全\",\"domain\":\"國家安全\",\"description\":\"從「電力即國力」的觀點，分析能源供應安全與備援能力如何影響台灣在地緣政治、經貿談判與產業布局上的韌性。\",\"relevance\":\"supporting\",\"evidence_ids\":[2,7],\"confidence\":\"medium\"},{\"topic_id\":\"t7\",\"name\":\"電價結構與政治經濟\",\"domain\":\"財政與公共經濟\",\"description\":\"檢視台灣民生與產業電價、補貼與凍漲政策，如何反映或扭曲能源成本，並對節能誘因與財政負擔造成影響。\",\"relevance\":\"supporting\",\"evidence_ids\":[8,9],\"confidence\":\"medium\"},{\"topic_id\":\"t8\",\"name\":\"能源政策的政黨競爭與意識形態\",\"domain\":\"政治學\",\"description\":\"分析不同政黨在核能、再生能源、煤氣比例等議題上的立場差異，以及意識形態如何形塑政策選項與社會分歧。\",\"relevance\":\"core\",\"evidence_ids\":[1,3,8,10],\"confidence\":\"high\"},{\"topic_id\":\"t9\",\"name\":\"環保與空污、健康風險\",\"domain\":\"環境健康\",\"description\":\"整理燃煤、天然氣以及再生能源設置對空氣品質、生態與居民健康的影響，並評估不同能源組合的環境代價。\",\"relevance\":\"supporting\",\"evidence_ids\":[2,4,5],\"confidence\":\"medium\"},{\"topic_id\":\"t10\",\"name\":\"再生能源設置的土地與社會衝突\",\"domain\":\"土地與地方治理\",\"description\":\"聚焦地面型太陽能、風機設置與漁業、農業、景觀、生態及地方居民之間的衝突與協商機制。\",\"relevance\":\"core\",\"evidence_ids\":[5,6],\"confidence\":\"high\"},{\"topic_id\":\"t11\",\"name\":\"能源轉型的產業機會與綠色成長\",\"domain\":\"產業與創新\",\"description\":\"探討再生能源、儲能、智慧電網與節能技術在台灣可能創造的產業與就業機會，以及「經濟日不落國」等口號與實際政策落差。\",\"relevance\":\"supporting\",\"evidence_ids\":[3,4,6,8],\"confidence\":\"medium\"},{\"topic_id\":\"t12\",\"name\":\"關鍵利害關係人與利益分配\",\"domain\":\"公共政策\",\"description\":\"盤點中央政府、地方政府、國營事業（如台電）、半導體與製造業者、再生能源開發商、環保團體與地方居民等角色及其利益衝突。\",\"relevance\":\"core\",\"evidence_ids\":[1,2,3,5,6,7,10],\"confidence\":\"high\"},{\"topic_id\":\"t13\",\"name\":\"國際能源轉型經驗比較（德國、日本、韓國）\",\"domain\":\"國際比較政策\",\"description\":\"比較德國能源轉型、日本核災後能源路線、韓國減核/再核等案例，找出台灣在制度設計與社會溝通上的可借鏡之處。\",\"relevance\":\"supporting\",\"evidence_ids\":[],\"confidence\":\"medium\"},{\"topic_id\":\"t14\",\"name\":\"電網基礎建設與儲能系統\",\"domain\":\"工程與基礎設施\",\"description\":\"分析台灣電網老化、區域供電不均與再生能源併網挑戰，以及儲能技術、智慧電網在提升穩定供電中的角色。\",\"relevance\":\"supporting\",\"evidence_ids\":[2,4,6,7],\"confidence\":\"medium\"},{\"topic_id\":\"t15\",\"name\":\"長期能源情境規劃與路徑模擬\",\"domain\":\"能源經濟與模型\",\"description\":\"檢視官方與學界對不同能源配比（核、氣、煤、再生）的情境模擬與成本效益分析，作為政策選擇的量化基礎。\",\"relevance\":\"supporting\",\"evidence_ids\":[],\"confidence\":\"medium\"},{\"topic_id\":\"t16\",\"name\":\"社會溝通、風險認知與信任\",\"domain\":\"社會學與傳播\",\"description\":\"探討政府在能源政策上資訊公開、風險溝通與參與機制，及媒體與社群如何影響大眾對缺電、核能與再生能源的認知。\",\"relevance\":\"core\",\"evidence_ids\":[1,2,3,8,10],\"confidence\":\"medium\"},{\"topic_id\":\"t17\",\"name\":\"國際貿易、碳邊境調整與供應鏈壓力\",\"domain\":\"國際經貿\",\"description\":\"說明歐盟CBAM等國際碳規範對台灣出口產業的壓力，如何反向推動國內能源結構調整與減碳。\",\"relevance\":\"supporting\",\"evidence_ids\":[4,9],\"confidence\":\"medium\"},{\"topic_id\":\"t18\",\"name\":\"能源技術創新與在地研發能力\",\"domain\":\"科技政策\",\"description\":\"評估台灣在儲能、氫能、再生能源設備製造與智慧能源管理等技術上的研發與產業化能力。\",\"relevance\":\"peripheral\",\"evidence_ids\":[4,6],\"confidence\":\"low\"},{\"topic_id\":\"t19\",\"name\":\"災害、極端氣候與能源系統韌性\",\"domain\":\"防災與韌性\",\"description\":\"分析颱風、地震與極端高溫等對發電與輸配電系統的衝擊，以及韌性規劃在能源政策中的重要性。\",\"relevance\":\"peripheral\",\"evidence_ids\":[],\"confidence\":\"low\"},{\"topic_id\":\"t20\",\"name\":\"地方能源自治與社區型能源模式\",\"domain\":\"治理模式\",\"description\":\"探討地方政府或社區參與的能源合作社、社區電廠等模式，是否能緩和地方反彈並提升再生能源接受度。\",\"relevance\":\"peripheral\",\"evidence_ids\":[],\"confidence\":\"medium\"}],\"relations\":[{\"relation_id\":\"r1\",\"source_topic_id\":\"t1\",\"target_topic_id\":\"t5\",\"relation_type\":\"causes\",\"description\":\"若電力供需吃緊與不穩定，會提高半導體與AI產業外移或減少投資的風險。\",\"evidence_ids\":[1,2,7,9],\"confidence\":\"high\"},{\"relation_id\":\"r2\",\"source_topic_id\":\"t2\",\"target_topic_id\":\"t1\",\"relation_type\":\"supports\",\"description\":\"非核家園政策設定了核能退場時間表，限制可用基載電力，助長社會對缺電風險的焦慮。\",\"evidence_ids\":[1,10],\"confidence\":\"medium\"},{\"relation_id\":\"r3\",\"source_topic_id\":\"t3\",\"target_topic_id\":\"t4\",\"relation_type\":\"part_of\",\"description\":\"再生能源的擴張是達成台灣淨零排放與能源轉型路徑的核心手段之一。\",\"evidence_ids\":[4,5,6],\"confidence\":\"high\"},{\"relation_id\":\"r4\",\"source_topic_id\":\"t3\",\"target_topic_id\":\"t1\",\"relation_type\":\"prevents\",\"description\":\"若再生能源依計畫達標並搭配電網與儲能，可在中長期緩解缺電壓力。\",\"evidence_ids\":[4,5,6,7],\"confidence\":\"medium\"},{\"relation_id\":\"r5\",\"source_topic_id\":\"t10\",\"target_topic_id\":\"t3\",\"relation_type\":\"prevents\",\"description\":\"土地與地方社會衝突會拖延或阻礙再生能源設置進度，使目標難以達成。\",\"evidence_ids\":[5,6],\"confidence\":\"high\"},{\"relation_id\":\"r6\",\"source_topic_id\":\"t8\",\"target_topic_id\":\"t2\",\"relation_type\":\"supports\",\"description\":\"政黨與意識形態競爭強化了非核家園政策的象徵意義，使其難以技術性調整。\",\"evidence_ids\":[1,3,10],\"confidence\":\"medium\"},{\"relation_id\":\"r7\",\"source_topic_id\":\"t8\",\"target_topic_id\":\"t3\",\"relation_type\":\"contradicts\",\"description\":\"當政黨過度強調象徵性能源目標時，可能忽略實際執行困難，形成政策口號與地面阻礙之間的矛盾。\",\"evidence_ids\":[3,5,8],\"confidence\":\"medium\"},{\"relation_id\":\"r8\",\"source_topic_id\":\"t7\",\"target_topic_id\":\"t4\",\"relation_type\":\"prevents\",\"description\":\"若電價長期被壓低，將削弱節能與投資低碳能源的經濟誘因，阻礙淨零與能源轉型。\",\"evidence_ids\":[8,9],\"confidence\":\"medium\"},{\"relation_id\":\"r9\",\"source_topic_id\":\"t12\",\"target_topic_id\":\"t10\",\"relation_type\":\"supports\",\"description\":\"各方利害關係人之間的利益分配與信任問題，是再生能源設置土地與社會衝突的主要來源。\",\"evidence_ids\":[3,5,6,10],\"confidence\":\"high\"},{\"relation_id\":\"r10\",\"source_topic_id\":\"t16\",\"target_topic_id\":\"t1\",\"relation_type\":\"causes\",\"description\":\"缺乏清楚的資訊與風險溝通，使民眾對缺電與跳電事件的體感風險升高，進一步政治化電力議題。\",\"evidence_ids\":[1,2,3,8,10],\"confidence\":\"medium\"},{\"relation_id\":\"r11\",\"source_topic_id\":\"t13\",\"target_topic_id\":\"t4\",\"relation_type\":\"analogous_to\",\"description\":\"德國、日本、韓國的能源轉型路線提供台灣在制定淨零與能源結構調整時的可比對參考。\",\"evidence_ids\":[],\"confidence\":\"medium\"},{\"relation_id\":\"r12\",\"source_topic_id\":\"t14\",\"target_topic_id\":\"t3\",\"relation_type\":\"enables\",\"description\":\"強化電網與導入儲能是支撐高比例再生能源並維持供電穩定的必要條件。\",\"evidence_ids\":[2,4,6,7],\"confidence\":\"high\"},{\"relation_id\":\"r13\",\"source_topic_id\":\"t17\",\"target_topic_id\":\"t4\",\"relation_type\":\"supports\",\"description\":\"國際貿易與碳邊境調整機制提高高碳產品成本壓力，促使台灣更積極推動淨零與能源轉型。\",\"evidence_ids\":[4,9],\"confidence\":\"medium\"},{\"relation_id\":\"r14\",\"source_topic_id\":\"t11\",\"target_topic_id\":\"t4\",\"relation_type\":\"supports\",\"description\":\"將能源轉型視為產業升級與綠色成長機會，有助於在政治上爭取對淨零政策的支持。\",\"evidence_ids\":[3,4,6,8],\"confidence\":\"medium\"},{\"relation_id\":\"r15\",\"source_topic_id\":\"t20\",\"target_topic_id\":\"t10\",\"relation_type\":\"prevents\",\"description\":\"若能發展地方能源自治與社區型能源模式，有機會降低再生能源設置時的在地衝突。\",\"evidence_ids\":[],\"confidence\":\"low\"},{\"relation_id\":\"r16\",\"source_topic_id\":\"t6\",\"target_topic_id\":\"t5\",\"relation_type\":\"supports\",\"description\":\"將電力視為國安資產，有助於凸顯穩定供電對維繫高科技產業鏈的重要性。\",\"evidence_ids\":[2,7,9],\"confidence\":\"medium\"},{\"relation_id\":\"r17\",\"source_topic_id\":\"t18\",\"target_topic_id\":\"t11\",\"relation_type\":\"supports\",\"description\":\"能源技術創新與在地研發能強化再生能源與節能產業的競爭力，創造新的成長動能。\",\"evidence_ids\":[4,6],\"confidence\":\"low\"},{\"relation_id\":\"r18\",\"source_topic_id\":\"t19\",\"target_topic_id\":\"t14\",\"relation_type\":\"supports\",\"description\":\"極端氣候與災害風險提升了強化電網與分散式能源系統的必要性。\",\"evidence_ids\":[],\"confidence\":\"low\"},{\"relation_id\":\"r19\",\"source_topic_id\":\"t15\",\"target_topic_id\":\"t2\",\"relation_type\":\"contradicts\",\"description\":\"部分長期能源情境模型顯示，在穩定供電與減碳前提下完全排除核能會顯著提高成本與風險，對非核家園路線形成挑戰。\",\"evidence_ids\":[],\"confidence\":\"low\"},{\"relation_id\":\"r20\",\"source_topic_id\":\"t15\",\"target_topic_id\":\"t3\",\"relation_type\":\"supports\",\"description\":\"情境分析常指出提升再生能源比重是兼顧減碳與能源自主的重要選項。\",\"evidence_ids\":[],\"confidence\":\"medium\"}],\"followup_questions\":[\"台灣過去十年實際發生的限電與大規模跳電事件，其主因是設備老化、操作失誤、極端氣候，還是結構性供電不足？\",\"非核家園政策若做技術性調整（如延役），在法律、政治與社會接受度上最大的障礙是什麼？\",\"目前再生能源裝置容量與發電占比的實際數據為何，與原先目標相比落差多大？\",\"半導體與AI產業未來十到二十年的用電需求預測為何，現有供電規劃是否足以因應？\",\"國際上有哪些成功降低地方再生能源衝突的治理模式，台灣是否已有試點案例？\",\"台灣電價若反映真實成本與碳排放，對不同所得族群與產業的影響為何，有哪些配套可減緩衝擊？\",\"德國、日本與韓國在能源轉型過程中，如何在核能去留、再生能源擴張與電價承受之間做取捨？\",\"台灣在國際碳邊境調整與供應鏈減碳壓力下，能源結構調整的時間壓力有多大？\"],\"search_seeds\":[{\"seed_id\":\"s1\",\"query\":\"台灣 電力 供需 現況 備轉容量 缺電 限電 事件 分析\",\"target_topic_id\":\"t1\",\"rationale\":\"釐清台灣是否存在結構性缺電，或是主因在於電網管理與極端氣候。\",\"source_strategy\":\"both\",\"priority\":\"high\",\"status\":\"pending\"},{\"seed_id\":\"s2\",\"query\":\"台灣 非核家園 政策 立法 過程 延役 公投 爭議\",\"target_topic_id\":\"t2\",\"rationale\":\"了解非核家園政策的法律基礎與政治攻防，作為評估政策可調整空間的基礎。\",\"source_strategy\":\"both\",\"priority\":\"high\",\"status\":\"pending\"},{\"seed_id\":\"s3\",\"query\":\"台灣 再生能源 裝置容量 太陽光電 離岸風電 進度 目標 達成率\",\"target_topic_id\":\"t3\",\"rationale\":\"確認再生能源發展是否如期達標，以及面臨的主要阻礙。\",\"source_strategy\":\"both\",\"priority\":\"high\",\"status\":\"pending\"},{\"seed_id\":\"s4\",\"query\":\"台灣 2050 淨零 排放 路徑 能源 結構 調整 政策 白皮書\",\"target_topic_id\":\"t4\",\"rationale\":\"掌握官方對淨零與能源轉型的中長期規劃與里程碑。\",\"source_strategy\":\"both\",\"priority\":\"medium\",\"status\":\"pending\"},{\"seed_id\":\"s5\",\"query\":\"台灣 半導體 用電 需求 預測 AI 數據中心 電網 影響\",\"target_topic_id\":\"t5\",\"rationale\":\"評估高科技產業擴張對未來電力需求與基礎設施的壓力。\",\"source_strategy\":\"both\",\"priority\":\"high\",\"status\":\"pending\"},{\"seed_id\":\"s6\",\"query\":\"台灣 電價 結構 補貼 凍漲 政策 對 能源 轉型 影響\",\"target_topic_id\":\"t7\",\"rationale\":\"了解電價政策如何影響節能與再生能源投資。\",\"source_strategy\":\"both\",\"priority\":\"medium\",\"status\":\"pending\"},{\"seed_id\":\"s7\",\"query\":\"台灣 再生能源 地面型 光電 土地 使用 衝突 地方 居民 抗爭 案例\",\"target_topic_id\":\"t10\",\"rationale\":\"蒐集具體地方衝突案例，分析成因與協商機制。\",\"source_strategy\":\"both\",\"priority\":\"high\",\"status\":\"pending\"},{\"seed_id\":\"s8\",\"query\":\"德國 日本 韓國 能源 轉型 核能 政策 再生能源 比較 研究\",\"target_topic_id\":\"t13\",\"rationale\":\"建立國際比較基準，評估台灣能源政策選項的相對風險與機會。\",\"source_strategy\":\"both\",\"priority\":\"medium\",\"status\":\"pending\"},{\"seed_id\":\"s9\",\"query\":\"台灣 電網 老化 儲能 系統 智慧 電網 建設 計畫\",\"target_topic_id\":\"t14\",\"rationale\":\"確認電網與儲能在政策與投資上的現況，以評估高比例再生能源的可行性。\",\"source_strategy\":\"both\",\"priority\":\"medium\",\"status\":\"pending\"},{\"seed_id\":\"s10\",\"query\":\"台灣 能源 政策 民意 調查 風險 認知 媒體 報導 案例 分析\",\"target_topic_id\":\"t16\",\"rationale\":\"分析社會對核能、再生能源與缺電的認知與信任來源。\",\"source_strategy\":\"both\",\"priority\":\"medium\",\"status\":\"pending\"},{\"seed_id\":\"s11\",\"query\":\"CBAM 碳邊境調整 台灣 出口 產業 影響 能源 結構 調整 壓力\",\"target_topic_id\":\"t17\",\"rationale\":\"釐清國際碳政策如何反向影響台灣國內能源政策。\",\"source_strategy\":\"both\",\"priority\":\"low\",\"status\":\"pending\"},{\"seed_id\":\"s12\",\"query\":\"台灣 社區 電廠 能源 合作社 地方 能源 自治 案例\",\"target_topic_id\":\"t20\",\"rationale\":\"尋找能降低地方衝突的替代治理與商業模式。\",\"source_strategy\":\"both\",\"priority\":\"low\",\"status\":\"pending\"}],\"version\":0,\"revision_history\":[],\"created_at\":\"2026-04-27T00:00:00Z\",\"last_refined_at\":\"2026-04-27T00:00:00Z\"}",
  "evidence_pool": {
    "1": {
      "url": "https://udn.com/news/story/7266/9144391",
      "year": "2025",
      "title": "光電三法三讀 環團意見分歧",
      "author": "聯合報",
      "snippet": "",
      "evidence_id": 1,
      "retrieved_at": "2026-05-27T06:33:52.628948",
      "source_domain": "udn.com",
      "iteration_origin": 1
    },
    "2": {
      "url": "https://news.ltn.com.tw/news/life/breakingnews/5224974",
      "year": "2025",
      "title": "盼終結地面型光電亂象 環團籲明訂禁建區、加嚴環評把關",
      "author": "自由時報",
      "snippet": "",
      "evidence_id": 2,
      "retrieved_at": "2026-05-27T06:33:52.629000",
      "source_domain": "news.ltn.com.tw",
      "iteration_origin": 1
    },
    "3": {
      "url": "https://udn.com/news/story/7238/9140278",
      "year": "2025",
      "title": "光電環評修法朝野協商 六大環團聯合聲明「擴大禁建恐矯枉過正」",
      "author": "聯合報",
      "snippet": "",
      "evidence_id": 3,
      "retrieved_at": "2026-05-27T06:33:52.629029",
      "source_domain": "udn.com",
      "iteration_origin": 1
    },
    "4": {
      "url": "https://www.chinatimes.com/realtimenews/20251114001911-263301",
      "year": "2025",
      "title": "光電環評門檻擬下修 環團憂恐矯枉過正：2公頃以下免環評",
      "author": "中國時報",
      "snippet": "",
      "evidence_id": 4,
      "retrieved_at": "2026-05-27T06:33:52.629056",
      "source_domain": "chinatimes.com",
      "iteration_origin": 1
    },
    "5": {
      "url": "https://e-info.org.tw/node/242527",
      "year": "2025",
      "title": "251117電子報｜立院三讀通過光電禁區、環評加嚴——對綠電影響大嗎？ 如何不必是「死局」？",
      "author": "環境資訊中心",
      "snippet": "",
      "evidence_id": 5,
      "retrieved_at": "2026-05-27T06:33:52.629083",
      "source_domain": "e-info.org.tw",
      "iteration_origin": 1
    },
    "6": {
      "url": "https://udn.com/news/story/6656/9082121",
      "year": "2025",
      "title": "監院調查揭光電申設7大問題 籲政院強化協調防範不法",
      "author": "聯合報",
      "snippet": "",
      "evidence_id": 6,
      "retrieved_at": "2026-05-27T06:33:52.629110",
      "source_domain": "udn.com",
      "iteration_origin": 1
    },
    "7": {
      "url": "https://news.ltn.com.tw/news/life/breakingnews/4905108",
      "year": "2025",
      "title": "不只15％！ 宜縣要求依污染總量分配 爭取花蓮和平電廠提高回饋金",
      "author": "自由時報",
      "snippet": "",
      "evidence_id": 7,
      "retrieved_at": "2026-05-27T06:33:52.629136",
      "source_domain": "news.ltn.com.tw",
      "iteration_origin": 1
    },
    "8": {
      "url": "https://e-info.org.tw/node/237125",
      "year": "2025",
      "title": "內政部放寬綠能用地今預告截止 學者呼籲暫緩、重申以農為本原則",
      "author": "環境資訊中心",
      "snippet": "",
      "evidence_id": 8,
      "retrieved_at": "2026-05-27T06:33:52.629180",
      "source_domain": "e-info.org.tw",
      "iteration_origin": 1
    },
    "9": {
      "url": "https://e-info.org.tw/node/240618",
      "year": "2025",
      "title": "芳苑與風機的距離 低頻噪音有什麼影響？",
      "author": "環境資訊中心",
      "snippet": "",
      "evidence_id": 9,
      "retrieved_at": "2026-05-27T06:37:17.088000",
      "source_domain": "e-info.org.tw",
      "iteration_origin": 2
    },
    "10": {
      "url": "https://www.chinatimes.com/realtimenews/20250824001988-263301",
      "year": "2025",
      "title": "宜蘭擬設14陸域風機 低頻噪音恐傷身 立委揚言抗爭到底",
      "author": "中國時報",
      "snippet": "",
      "evidence_id": 10,
      "retrieved_at": "2026-05-27T06:37:17.088062",
      "source_domain": "chinatimes.com",
      "iteration_origin": 2
    },
    "11": {
      "url": "https://www.chinatimes.com/realtimenews/20250825000511-260402",
      "year": "2025",
      "title": "陸域風機9／2說明會 藍委率眾抗議",
      "author": "中國時報",
      "snippet": "",
      "evidence_id": 11,
      "retrieved_at": "2026-05-27T06:37:17.088087",
      "source_domain": "chinatimes.com",
      "iteration_origin": 2
    },
    "12": {
      "url": "https://e-info.org.tw/node/241124",
      "year": "2025",
      "title": "250416電子報｜台東海岸58座風機開發案輿論發酵 彭啟明：不支持陸域風電",
      "author": "環境資訊中心",
      "snippet": "",
      "evidence_id": 12,
      "retrieved_at": "2026-05-27T06:50:25.482316",
      "source_domain": "e-info.org.tw",
      "iteration_origin": 2
    },
    "13": {
      "url": "https://e-info.org.tw/node/234209",
      "year": "2025",
      "title": "【聯合聲明】綠能發展要順利 環評門檻應加嚴",
      "author": "環境資訊中心",
      "snippet": "",
      "evidence_id": 13,
      "retrieved_at": "2026-05-27T06:50:25.482376",
      "source_domain": "e-info.org.tw",
      "iteration_origin": 2
    },
    "14": {
      "url": "https://e-info.org.tw/node/241123",
      "year": "2025",
      "title": "農村社區靠屋頂、水圳發電當老闆 美濃第一座公民電廠開催中",
      "author": "環境資訊中心",
      "snippet": "",
      "evidence_id": 14,
      "retrieved_at": "2026-05-27T06:50:25.482412",
      "source_domain": "e-info.org.tw",
      "iteration_origin": 2
    },
    "15": {
      "url": "https://www.chinatimes.com/realtimenews/20240120002655-260421?chdtv",
      "year": "2024",
      "title": "農電共融由民間主導！屏東首個「公民電廠合作社」誕生",
      "author": "中國時報",
      "snippet": "",
      "evidence_id": 15,
      "retrieved_at": "2026-05-27T06:51:56.201621",
      "source_domain": "chinatimes.com",
      "iteration_origin": 1
    },
    "16": {
      "url": "https://www.chinatimes.com/newspapers/20240121000464-260107?chdtv",
      "year": "2024",
      "title": "屏東首個 大武山公民電廠合作社成立",
      "author": "中國時報",
      "snippet": "",
      "evidence_id": 16,
      "retrieved_at": "2026-05-27T06:51:56.201802",
      "source_domain": "chinatimes.com",
      "iteration_origin": 1
    },
    "17": {
      "url": "https://e-info.org.tw/node/237211",
      "year": "2025",
      "title": "苗栗小光電八成位於石虎熱點 環團走訪三縣市提建言",
      "author": "環境資訊中心",
      "snippet": "",
      "evidence_id": 17,
      "retrieved_at": "2026-05-27T06:51:56.201867",
      "source_domain": "e-info.org.tw",
      "iteration_origin": 1
    },
    "18": {
      "url": "https://e-info.org.tw/node/242328",
      "year": "2025",
      "title": "風電光電的困局 綠能開發問題在哪？",
      "author": "環境資訊中心",
      "snippet": "",
      "evidence_id": 18,
      "retrieved_at": "2026-05-27T06:51:56.201895",
      "source_domain": "e-info.org.tw",
      "iteration_origin": 1
    },
    "19": {
      "url": "https://udn.com/news/story/7266/9098394",
      "year": "2025",
      "title": "影／環團提十大訴求 呼籲立法扭轉光電亂象",
      "author": "聯合報",
      "snippet": "",
      "evidence_id": 19,
      "retrieved_at": "2026-05-27T06:53:53.431587",
      "source_domain": "udn.com",
      "iteration_origin": 2
    },
    "20": {
      "url": "https://www.moea.gov.tw/MNS/populace/news/News.aspx?kind=1&menu_id=40&news_id=120897",
      "year": "2025",
      "title": "屋頂優先環境永續 穩健推動太陽光電發展",
      "author": "經濟部",
      "snippet": "",
      "evidence_id": 20,
      "retrieved_at": "2026-05-27T06:53:53.431624",
      "source_domain": "moea.gov.tw",
      "iteration_origin": 2
    },
    "21": {
      "url": "https://esg.businesstoday.com.tw/article/category/180686/post/202511140003",
      "year": "2025",
      "title": "環評法修法對綠電衝擊多大？七大光電公協會示警：恐波及供電穩定、削弱半導體競爭力與 RE100 履約",
      "author": "今周刊",
      "snippet": "",
      "evidence_id": 21,
      "retrieved_at": "2026-05-27T06:53:53.431644",
      "source_domain": "esg.businesstoday.com.tw",
      "iteration_origin": 2
    }
  },
  "last_completed_section_index": -1,
  "_source": "prod session 58227766 / 能源轉型下的農漁村綠能衝突 / 2026-05-27"
}